{"is_source_file": false, "format": "", "description": "", "external_files": [], "external_methods": [], "published": [], "classes": [], "methods": [], "calls": [], "search-terms": [], "state": 2, "file_id": 5, "knowledge_revision": 136, "git_revision": "e8778727235574fa7d7a6efd932fd4d1bdd7fbe8", "hash": "c73cbfc856d32f6257f1ed183310c504", "format-version": 4, "code-base-name": "frontend_react_js", "filename": "frontend_react_js/public/manifest.json", "revision_history": [{"136": "e8778727235574fa7d7a6efd932fd4d1bdd7fbe8"}]}