{"is_source_file": false, "format": null, "description": "", "external_files": [], "external_methods": [], "published": [], "classes": [], "methods": [], "calls": [], "search-terms": [], "state": 2, "file_id": 6, "knowledge_revision": 78, "git_revision": "da3d5fc8d1b910d0ef22122fce3530e5b264f1dd", "hash": "c7a979ffc235528fd4837a1328fdc7a1", "format-version": 4, "code-base-name": "frontend_react_js", "filename": "frontend_react_js/public/index.html", "revision_history": [{"78": "da3d5fc8d1b910d0ef22122fce3530e5b264f1dd"}]}