{"is_source_file": false, "format": "", "description": "", "external_files": [], "external_methods": [], "published": [], "classes": [], "methods": [], "calls": [], "search-terms": [], "state": 2, "file_id": 3, "knowledge_revision": 243, "git_revision": "6fb67e4fb4b9dbb38f9818bbac4df698d94ff430", "hash": "142e51b337d090a069a5fc45be9360ee", "format-version": 4, "code-base-name": "frontend_react_js", "filename": "frontend_react_js/package.json", "revision_history": [{"243": "6fb67e4fb4b9dbb38f9818bbac4df698d94ff430"}]}