{"is_source_file": false, "format": "", "description": "", "external_files": [], "external_methods": [], "published": [], "classes": [], "methods": [], "calls": [], "search-terms": [], "state": 2, "file_id": 3, "knowledge_revision": 93, "git_revision": "358b78614d3b02f2e0d565cbd90c50b797eb8836", "hash": "d409ec7d6d540ee61626403bc83b51a2", "format-version": 4, "code-base-name": "frontend_react_js", "filename": "frontend_react_js/package.json", "revision_history": [{"93": "358b78614d3b02f2e0d565cbd90c50b797eb8836"}]}